somnetics_seamless_utils/__init__.py
somnetics_seamless_utils/config.py
somnetics_seamless_utils/elastic.py
somnetics_seamless_utils/message.py
somnetics_seamless_utils/objectstore.py
somnetics_seamless_utils/requirements.txt
somnetics_seamless_utils/service.py
somnetics_seamless_utils-0.0.4.dist-info/METADATA
somnetics_seamless_utils-0.0.4.dist-info/WHEEL
somnetics_seamless_utils-0.0.4.dist-info/licenses/LICENSE
somnetics_seamless_utils-0.0.4.dist-info/RECORD
